Workbook

Sheet Problems
A1: ID | B1: Section | C1: Problem | D1: What to do | E1: Done when | F1: Contribution | G1: Phase | H1: Priority | I1: Difficulty (1-5) | J1: Est. weeks | K1: Depends on (IDs) | L1: Status | M1: Notes
A2: 1 | B2: A. Foundations | C2: Verify the curvature claim | D2: Re-derive that the per-event loss l_i(θ) = −log(a_iᵀθ) + b_iᵀθ has a rank-one Hessian and is not exp-concave when b_i is not parallel to a_i. Then find the correct curvature statement: look at the expected loss, whose Hessian is the Fisher information per unit time, and bound its smallest eigenvalue on Θ_ε = {μ ≥ μ_min, α ≥ 0, n ≤ 1−ε}. | E2: A short written lemma with the counterexample, plus the corrected curvature statement and a bound on the smallest eigenvalue. | F2: C1 | G2: P1 Core feasibility | H2: Critical | I2: 3 | J2: 1 | L2: Done | M2: Draft done 2026-10-24. Hessian a a^T/lam^2 is rank one; exp-concavity fails whenever b not parallel to a (counterexample checked numerically). Corrected statement: expected-loss Hessian >= c(theta)^-2 I(theta*), and lam_min(I) >= (eps/mu)*inf_v(E|v^T a|)^2 by Cauchy-Schwarz; K=1 exact check gives lam_min ~ eps/mu. Needs your own re-derivation. Open: alpha*_k=0 case, stationarity/burn-in. See problem01_curvature_lemma.md
A3: 2 | B3: A. Foundations | C3: Identifiability of the dictionary | D3: On a fixed β-grid, decide whether the weights α are identifiable, i.e. whether the Fisher information I(θ) is nonsingular. Nearby β_k make the exponentials almost collinear, so the condition number grows with K and with grid density. Quantify it. | E3: An explicit lower bound on λ_min(I(θ)), or on the condition number, in terms of K and the grid ratio. | F3: C1 | G3: P2 Complete upper bound | H3: High | I3: 3 | J3: 1.5 | K3: 1 | L3: Done | M3: 25 Oct 2026. problem02_identifiability.md; code/p2_window_bound.py, p2_lemma3_check.py, p2_gram_bound.py, p2_truncation_check.py, p2_truncation_bound.py. Fixed a thinning bug in p2_identifiability.py (had made lam_min ~10x too small for K>=2). Findings (mu=1, beta=r^(k-1), MC 60-80k events): K>=2 lam_min does NOT shrink with eps (K=2: ~0.045 at r=2, ~0.065 at r=4), cond ~ 1/eps (K=1: eps^-2); lam_min falls ~10x per added exponential (r=2: 0.069, 0.046, 0.0045 for K=1,2,3 at eps=0.1). Lower bounds: (1) Gram-matrix route is rigorous but useless (1e-6 to 1e-16 of truth, decays like eps^(2K+1)). (2) Theorem T (truncation + Lemma-B moments): lam_min(I) >= (1/L)[lam_min(M) - sqrt(E|a|^4) sqrt(E lam^p / L^p)], M = E[a a^T] exact via a K^2 linear system (matches MC to 1-3%); bound is 2e-3 to 5e-2 of the MC lam_min for K<=3 and non-vacuous; pure truncation without tail penalty would be within 2-8x. Open: closed-form formula in K and grid ratio, sharper tail bound, eps-sharpness for K>=2. Depends on Lemma B (Problem 3 draft). Draft, not independently verified. CLOSED 25 Oct (Done): closed-form chain in K and grid ratio r: Cov(S) >= (E lam/4) G (G=1/(b_i+b_j), spectral), exact E S_k = mu/(eps b_k), lam_min(M) >= lam_min(C)/(1+2|m|^2), Cauchy inverse in closed form, then truncation with Lemma-1' moments; valid but 1e3-1e8 below truth (code/p2_closed_chain.py). Sharp scaling = three-tier structure (Problem 12), heuristic.
A4: 3 | B4: A. Foundations | C4: Uniform moment and ergodicity bounds as n → 1 | D4: Bound E[λ^p] and the mixing rate (spectral gap) of the Markov state (S_1, …, S_K) uniformly as n → 1. Start from E[λ] = μ/(1−n) and find how the spectral gap shrinks with ε. Without this, no concentration argument closes. | E4: A lemma with explicit ε-dependence for the moment bounds and for the mixing or contraction rate. | F4: C1, C2 | G4: P1 Core feasibility | H4: Critical | I4: 4 | J4: 3 | L4: Done | M4: Draft done 2026-10-24. Key identity A Z = mu - eps*lam for Z=sum(alpha_k/beta_k)S_k. Moments: E Z^p <= C_p eps^-p for all p (induction, constants depend on mu,beta_min,beta_max); sub-exponential tail E exp(eps Z/e) <= 2exp(4mu/(e beta_min)). Contraction in weighted Wasserstein at rate >= eps*beta_min (monotone coupling); slowest mean mode gamma ~ eps/sum(alpha/beta^2), so mixing ~1/(eps*beta), independent of mu. Checked against exact moments and simulation. Needs your re-derivation. Open: true L2 gap, grid-uniform constants, sup over time horizon, non-stationary start. See problem03_moments_mixing.md
A5: 4 | B5: A. Foundations | C5: Projection onto Θ_ε | D5: Design a cheap projection, in the Fisher or ONS metric, onto the polytope {μ ≥ μ_min, α ≥ 0, Σ α_k/β_k ≤ 1−ε}. This is an algorithm problem rather than a theory one, but it affects the constants. | E5: An algorithm with O(K) or O(K log K) cost, a note on its effect on the regret constants, and a working implementation. | F5: C1 | G5: P2 Complete upper bound | H5: Medium | I5: 2 | J5: 1 | K5: 1 | L5: Done | M5: 24-25 Oct 2026. problem04_projection.md, code/p4_projection.py. Exact projection onto {mu>=mu_min, alpha>=0, sum alpha_k/beta_k<=1-eps} in a DIAGONAL metric: mu separable; alpha_k = max(0, y_k - tau*w_k/d_k), tau from sorted breakpoints, O(K log K); matches SLSQP on 300 random instances (4e-6); <1 ms for K up to 1e4. Regret-constant effect: non-expansive in the update's own metric, so no extra constant; the cost is cond(D^-1/2 I D^-1/2). K=1: universal ~5.83 (rho^2->1/2), independent of eps (raw ~1e6 at eps=1e-3). K>=2 (corrected 25 Oct after fixing a simulator bug): scaled cond only 1.2-3x below raw and still grows as eps falls (K=2,r=2: 118->368; K=3: 765->2477), so a diagonal metric is NOT enough for K>=2. Open: dense-metric projection (QP, ~O(K^2)), O(K) version, K>=2 preconditioner. Status In progress because 'Done when' asks for the Fisher/ONS metric. UPDATE 25 Oct (problem05_circularity.md): for K=1 the diagonal clip is NOT adequate: it violates non-expansiveness in 0.7-4.6% of steps and inflates regret ~10x when the box is tight (E R_n 16 vs 3.5 at eps=.1; 79 vs 5.4 at eps=.03). Exact F-norm projection onto a box is O(1) for K=1 (edge minimisers + corners) and had 0 violations in 24 configs. Use it. CLOSED 25 Oct (Done): dense F-norm projection for any K (BVLS + bisection on the budget multiplier): matches brute force to 5e-14, non-expansive (0 violations in 2000 pairs), O(K^3) per inner solve (19 ms K=2, 97 ms K=5); the diagonal O(K log K) algorithm remains for the diagonal metric (code/p4_dense_projection.py).
A6: 5 | B6: B. Upper bound | C6: Stochastic ONS or recursive-MLE analysis | D6: Prove a regret or excess-risk bound for the Fisher-preconditioned update when data come from the true Hawkes law (or a nearby one). Tools: the score is a martingale difference, Freedman-type concentration, and iterates that are adapted to the path. | E6: A theorem with proof, in expectation or with high probability, under stated assumptions. | F6: C1, C2 | G6: P1 Core feasibility | H6: Critical | I6: 5 | J6: 4 | K6: 1, 3, 4 | L6: Done | M6: 25 Oct 2026. problem05_online_newton.md; code/p5_*.py. First pass, K=1 only. Proposition 1 (rigorous, short): for the unprojected Fisher-scoring/online-Newton update, E<g_i,v_i | past> = E[v_i' dF_i v_i | past] exactly (first-event compensator identity), hence E R_n <= ||th_1-th*||^2_{F_0} + E sum g_i' F_i^-1 g_i, no exp-concavity needed. Checked numerically (pathwise identity to 1e-13; expectation identity within SE; bound ~2x loose). Empirical: regret slope (d/2) in log n; E[R_n - log T_n] ~ flat in eps (-1.2,-2.3,-2.4,-2.8 for eps=.3,.1,.03,.01): no visible +C log(1/eps) in time units; apparent 0.5/eps burn-in cost was the prior term rho0*|th_1-th*|^2, vanishes with a weak prior. NOT proven: bound on G (needs leverage bound a'F^-1 a/lam = O(1) and local control, i.e. Problem 7), sharp constant 1/2 (needs localisation), projected algorithm (diag projection not non-expansive in F-norm; unprojected iterates exit Theta_eps in 55-85% of runs), K>=2, high-probability version. Draft, not independently verified. UPDATE 25 Oct: problem05_fisher_concentration.md (K=1, oracle information): Lemma F1 var(int h(S_t)dt) <= 2T Lip sqrt(m) sigma_S/gamma via the Problem-3 contraction; Lemma F2 two-interval bound J_T >= (O/L) Q (exact, deterministic); Theorem F: J_T >= (mT/4L) Q w.p. >=1-2q for all T>=T0=16 sigma_S/(rho gamma m^1.5 q) = O(1/(beta eps)), so Theorem-7 leverage assumptions hold w.h.p. given (L1). Numerics: variance bound holds with 500-1500x margin; pathwise leverage bound 0 violations in ~1300 checks; rigorous T0*gamma ~ 4e5 vs empirical ~20-50 (Chebyshev, 1e4x conservative). OPEN: circularity (L1 needs consistency which needs the information bound), Assumption M (pi-mass of bumps, numerical), exponential tails, projection, K>=2. UPDATE 25 Oct (problem05_circularity.md): circularity avoided by design, not by a consistency bootstrap: compact box Theta_c known a priori + exact F-norm projection => (L1) holds deterministically (c+=max(mu_hi/mu*,al_hi/al*), c-=min(...)); Prop 1 survives projection (non-expansiveness in F-norm); leverage w.h.p. after T0=O(1/(beta eps)) via Theorem F. Numerics (K=1): R_n - log T_n between -4.4 and -0.5 in 24 configs, 0 non-expansiveness violations. Sketched only: stopping-time localisation of the w.h.p. event; burn-in term crude. OPEN: true bootstrap (c->1), K>=2 (QP projection), a priori scale knowledge, exponential tails. UPDATE 25 Oct (problem05_bootstrap.md): TRUE BOOTSTRAP, K=1, two-stage, polynomial tails. Stage 1 with box constants: pathwise D_j <= D0' - X - M + G (M martingale, E m^2 <= (4/c-) E[v'dF v]); Doob L2 + Markov => P(sup D_j >= 3x) <= (1+16/c0-) Gamma/x, Gamma=O(d log T); with F >= lam_T I this forces the iterates into R(delta) for t>=T1 when delta^2 >= 24(1+16/c0-)c0+ L Gamma/(q m lamQ rho*^2 T1) (T1 gamma ~ d log T1/delta^2). Stage 2: with c+-=1+-delta, A->1, B->0, psi-factor 2 -> 1+O(delta): regret (d/2+o(1)) log T on the good event. Numerics: pathwise inequality margin 1e-14; E sum m^2/E X ~4; sup D_j <=14; last exit time from R(delta) ~ 1-3/(delta^2 gamma), slope of E R_n in log T ~0.9 (target d/2=1). NOT proved: expected regret with sharp constant (needs exponential tails; bad event only ~1/T1), localisation bookkeeping, K>=2, a-priori box. UPDATE 25 Oct (problem05_exponential_tails.md): exponential tails. E1 exact identities (eps*Lam_T = mu T + n M'_T - n dS; Poisson eq u=(s-ES)/gamma), verified 1e-14. E2 Lam_T tails exp(-eta^2 mu eps T/2n^2). E3 occupation functionals via Poisson equation + Freedman: P(int h <= Tm/2) <= 3 exp(-c T gamma), c=m^2 mu/(32 kappa^2 (1+eta) beta) ~3e-7 (empirical decay ~0.04-0.056 per unit T*gamma: bound valid but 1e5x pessimistic). E4 Newton martingale: with prob>=1-e^-x, -M_t <= X_t + x/theta for all t (theta=min(1/(2k1), c-/2.87)) so sup D_j <= D0' + x/theta + G_n. Theorem C-exp: bootstrap with T1 = O((ln(1/q)+d log T)/(gamma delta^2)). NOT done: E5 (exp bound on G_n, martingale part of score sum) in detail; expected regret with sharp constant needs episode/restart argument (union bound would pay crude linear rate on [0, T_c ~ log T_n]); constants; K>=2. REASSESSMENT 25 Oct (novelty_reassessment.md): C2's 'C log(1/eps)' should be made explicit: conjecture regret = (d/2) log T + (1/2) log det I(theta*;eps) + O(1) in time units, with (1/2) log det I ~ ((1-k)^+/2) log(1/eps), k=2*mu*m (m=mean lifetime). Exact K=1 slopes confirm the information side (0.40 for k0=0.2); the regret side is DISFAVOURED by a 100-rep test (k0=0.2, E[R - log T] = -3.44+-0.10 at eps=0.3 vs -3.19+-0.32 at eps=0.01, against +1.30 predicted); conjecture withdrawn from the headline. Caveat: the test starts at theta*, so it cannot probe a Bayes/redundancy lower-bound constant. E5 + EXPECTED REGRET 25 Oct (problem05_E5_expected_regret.md, K1_main_results.md): E5 PROVED (Lemmas E5a-d, Prop E5: G_n <= (1+o(1)) logdet + o(1)x + B_X X w.p. >= 1-4e^-x; pathwise inequalities checked, 0 violations in 1.4e6 gaps). Found+fixed a flaw in Theorem 7/Lemma 7c: 'gap leverage <= xbar a.s.' cannot hold (depends on Exp(1) variable); truncation fixes it. Theorem R (K=1): E R_n <= (1/2+O(delta+eta)) d ln T + C, C independent of n, via charging bad events to their own time (no episode union bound); PROVED MODULO Thm F-exp, Assumption M (numerical), known box, and unwritten optional-stopping across random restarts. Rate constants ~1e5 worse than observed. K>=2 open. DEPENDENCIES 25 Oct (K1_completion.md): optional stopping closed (predictable good-gap indicators replace restarts); integrability in Thm F-exp closed; Assumption M closed for eps<=eps_M via the Gamma comparator of Thm T (E_Gamma h = 0.164, 0.044 vs simulated 0.15, 0.05); C(eps)=O(mu d ln(1/(eps delta))/(beta eps^2 delta^2)) (order only). Still assumed: known box; K>=2 open; constants conservative; Thm T itself is a proof outline with numerically verified estimates. ASSUMPTION M certified 25 Oct (thmT_explicit_constants.md): K=1, k0=2, mu=beta=1: m>=0.0248 for eps<=1e-4 (E_Gamma h = 0.164, 0.0444 minus TV<=0.0196). EXTENSIONS 25 Oct (assumptionM_exact.md, box_cost_and_lower_bound.md, K2_regret_chain.md): (1) Assumption M certified by exact Fourier quadrature for K=1, eps<=0.3, k0 in [0.6,4] (m>=0.032); (2) box cost: polynomial in c+,1/c-, empirically ~s^2 at rho0=1 (prior effect), leading constant box-free; scale of mu* not learnable at eps=c/T; (3) K>=2: chain carries over, Assumption M replaced by computable lambda_L (Thm FK), Thm R^(K) (K+1)/2 ln T + C_K, constants uninformative, K=2 slope ~1.3 vs 1.5 [N]; (4) minimax lower bound (d/2)ln n - O(ln ln n) for ANY predictor, conditional on uniformity (U). LaTeX master document: latex/hawkes_master.tex (not compiled). CLOSED 25 Oct (Done): Theorem HP (problem05_07_closure.md): with prob >= 1-6e^-x-P(E^c), R_n <= psi_max(2 i0+3x) + 4[D0' + x/theta + G_n(x)]; plus expected-regret Thm R (sharp constant). Assumptions: known compact convex Theta_c, leverage event, Assumption M (certified K=1) / lambda_L (K>=2). FINAL AUDIT 25 Oct (final_audit.md): fixed constant in Lemma E5c (xbar = lbar m/(c^- mu*), not c^+), replaced loose general-K Lemma E1 by the exact Z_c identity; K=2 pathwise Newton/martingale inequalities verified (code/p5_k2_pathwise_check.py).
A7: 6 | B7: B. Upper bound | C7: Make the ε-dependence explicit | D7: Track how the gradient bound, the curvature constant and the burn-in scale with ε and μ. Target form: (d/2) log T + C log(1/ε) + burn-in(με) with d = K+1. Decide what burn-in is really needed (probably of order 1/(με) in time or events). | E7: A theorem statement with every constant written as a function of ε, μ, K and the β-grid. | F7: C2 | G7: P2 Complete upper bound | H7: High | I7: 4 | J7: 3 | K7: 3, 5 | L7: Not started
A8: 7 | B8: B. Upper bound | C8: Handle the compensator term | D8: The gradient has the form −a_i/λ_i + b_i. Prove that both parts concentrate jointly with zero mean at θ*, given that b_i is not parallel to a_i. | E8: A lemma bounding the joint deviation of the two gradient components. | F8: C1 | G8: P2 Complete upper bound | H8: High | I8: 3 | J8: 2 | K8: 5 | L8: Done | M8: 25 Oct 2026. problem07_leverage.md; code/p5_leverage.py, p5_theorem_check.py, p5_component_check.py. K=1 only. Split gradient g = s (score at theta*) + h (drift). Lemma 7a (rigorous): E[s|past]=0, E[s s'|past]=E[dJ] (stopped martingale). Lemma 7b: E[h'F^-1 h] <= (ell/mu_min) E[v'dF v], ell = sup_u phi'F^-1 phi/lam* (point leverage). Lemma 7c: tr(F^-1 dF) <= r(x) logdet increment, r(x)=x/log(1+x) (gap leverage x). Theorem 7 (conditional on a.s. L1-L3): E R_n <= [P0 + (1+eta) c+ r(x) E logdet(F_n/F_0)]/(1-B), B=(1+1/eta) ell/mu_min<1, closing the gradient-norm term of Problem 5 (growth ~ d log T, constant ~3-6x too big). Leverage scale: worst case is the quiet gap, ell ~ [F^-1]_mumu/mu* ~ (k-1)/(eps T), so B<1 needs ~4(k-1)/(eps^2 mu_min) events: leverage burn-in ~1/eps^2 events (matches Problem 3 mixing; observed medians 1520 at eps=.1, 10086 at eps=.03). Numerics: all three lemmas verified; drift term is negligible in practice (0.02 vs bound 3); full bound valid but 15-40x loose. NOT done: L1-L3 as stopping-time/high-probability statements (needs Fisher concentration, Problems 2-3), projection, K>=2, sharp constant. Draft, not independently verified. UPDATE 25 Oct: problem05_fisher_concentration.md (K=1, oracle information): Lemma F1 var(int h(S_t)dt) <= 2T Lip sqrt(m) sigma_S/gamma via the Problem-3 contraction; Lemma F2 two-interval bound J_T >= (O/L) Q (exact, deterministic); Theorem F: J_T >= (mT/4L) Q w.p. >=1-2q for all T>=T0=16 sigma_S/(rho gamma m^1.5 q) = O(1/(beta eps)), so Theorem-7 leverage assumptions hold w.h.p. given (L1). Numerics: variance bound holds with 500-1500x margin; pathwise leverage bound 0 violations in ~1300 checks; rigorous T0*gamma ~ 4e5 vs empirical ~20-50 (Chebyshev, 1e4x conservative). OPEN: circularity (L1 needs consistency which needs the information bound), Assumption M (pi-mass of bumps, numerical), exponential tails, projection, K>=2. UPDATE 25 Oct: (L1) now holds by construction for the compact-box exact-projection algorithm (problem05_circularity.md); F >= F0 + J/c+ verified PSD in all runs. Remaining: localisation bookkeeping. UPDATE 25 Oct: bootstrap done at polynomial-tail level (problem05_bootstrap.md); remaining for the leverage assumptions: exponential tails, localisation, K>=2. UPDATE 25 Oct: exponential-tail versions of Theorem F and the bootstrap in problem05_exponential_tails.md (G_n control sketched only). CLOSED 25 Oct (Done): Lemma JD (problem05_07_closure.md): joint zero mean and covariance E dJ (non-degenerate since b not parallel to a), pathwise |s|^2_{F^-1} <= (2 lbar/mu)(1+E^2), tail e^-m, cumulative exponential bound (E5b); 0 violations in 1.44e6 gaps.
A9: 8 | B9: B. Upper bound | C9: Decide the notion of regret | D9: Log-loss regret against the best fixed θ* is not the same as parameter error. State both, and either prove the link between them or choose one as the headline result. | E9: A precise definition used consistently in all theorems, and a lemma connecting the two notions if both are kept. | F9: C2 | G9: P2 Complete upper bound | H9: Medium | I9: 2 | J9: 1 | K9: 5 | L9: Not started
A10: 9 | B10: C. Lower bound and information limits | C10: Two-point lower bound for online estimation | D10: Adapt the kernel-agnostic bound KL ≲ δ² T μ (1−n) to exponential dictionaries, then convert it into a regret or minimax statement. Check that it matches your upper bound in ε. | E10: A lower-bound theorem, and a comparison table showing where upper and lower bounds match or differ in ε, μ and T. | F10: C3 | G10: P3 Lower bound and simulation | H10: High | I10: 4 | J10: 3 | K10: 6, 10 | L10: Not started | M10: LITERATURE 25 Oct: the two-point KL bound is already Herrera-Marin arXiv 2609.38268 Thm 2.2 + Cor 2.3 (empty start, shared mu and kernel shape, any normalised shape incl. sums of exponentials; unrefereed). Re-derived and tested on K=1 (bound held in 12/12 configs, 2-7x loose). Novelty here must come from online-estimator regret or other directions (individual alpha_k, stationary start). REASSESSMENT 25 Oct: as written this problem (two-point bound) is prior art (Herrera-Marin Thm 2.2). Suggested replacement: (a) regret lower bound for sequential estimators >= (d/2) log T + (1/2) log det I - O(1); (b) identifiability map / matching UPPER bound on lambda_min(I) for the K-dictionary. Neither is proved; literature on regret lower bounds for point processes not yet searched.
A11: 10 | B11: C. Lower bound and information limits | C11: Fisher information as n → 1 for K = 1 | D11: Compute I(μ, α) for a single exponential with fixed β in closed form, using the stationary law of λ or the CIR scaling limit. This is the quickest test of whether items 9 and 11 are tractable. | E11: Closed-form (or asymptotic) Fisher information, with its behaviour as ε → 0 stated clearly. | F11: C3, C4 | G11: P1 Core feasibility | H11: Critical | I11: 3 | J11: 1.5 | L11: Done | M11: Revised 2026-10-25. K=1 near-critical asymptotics of m=E[1/lam] now PROVED (Theorem A: k>1 m~2eps/(2mu-beta); k=1 m~(2/beta)eps ln(1/eps); k<1 m~C eps^k). Correction: total information from a cold start is NOT T*I(theta*): mu-information always diverges (rigorous >= ln(1+beta_max T)/(mu beta_max), any K); dichotomy is log vs polynomial divergence (numerics: slope 2.03 for k=2, ~ln^2 T at k=1, T^(1-k) for k<1); bounded only under stationary start. K>=2: MC consistent, no proof. Cold-start coefficients conjectural. Needs your re-derivation. See problem10_fisher_k1.md and problem10_rigorous.md VERIFICATION 25 Oct (verification_thmA_E_F.md): Theorem A re-derived step by step and tested: CORRECT. Step 2 has two inadequate justifications (x>=1.5 boundedness needs convexity of h; 'denominator <= alpha x^2' does not follow from the displayed bounds) - both statements are true (numerically sup 2.07/alpha resp. 0.667) and repairable. Limits confirmed: m/eps = 1.998 (k0=2), m/eps^k0 = 5.93 -> 6.05 (k0=0.6), m/(eps ln 1/eps) = 1.945 -> 2 (k0=1). UPDATE 25 Oct (theoremA_step2_and_stationary_tv.md): Theorem A Step 2 REPAIRED (Lemma 2: D_eps<=2.08/alpha for all s via convexity of h; D_eps>=0.166/alpha for s>=1/alpha, eps<=1/4, via exact factor r<=1/3 and monotone h/x^2). Theorem A now fully justified; constants verified numerically. LITERATURE 25 Oct (literature_search_report.md): my exact K=1 Hawkes Fisher matrix converges (relative diff ~ eps) to the CIR Fisher matrix of Ben Alaya-Kebaier-Tran Thm 2.1 under (a,b)=(beta mu, beta eps), 2 sigma=beta^2; the conjectured cold-start coefficient 2/(beta(2mu-beta)) equals the CIR critical-case information rate of their Cor 2.3(i). So the K=1 information structure is the Hawkes prelimit of classical CIR theory (fixed regimes); no local-to-critical CIR result found.
A12: 11 | B12: C. Lower bound and information limits | C12: Light-tailed baseline information dichotomy | D12: Prove when information about μ diverges or stays bounded in the nearly unstable regime 1−n_T ≍ T⁻¹ for exponential kernels. The CIR limit has a Gamma stationary law; the open step is the case where its shape parameter exceeds 1. Hardest and most novel item on the list. | E12: A theorem (or a clear counterexample) giving the dichotomy, with the role of the shape parameter explicit. | F12: C4 | G12: P4 Stretch and validation | H12: High | I12: 5 | J12: 5 | K12: 3, 10 | L12: Done | M12: Draft done 2026-10-25 (needs your re-derivation). DECISION: C4 uses STATIONARY observation, dichotomy = bounded vs divergent. Rigorous: K=1 full dichotomy (Thm A, B); ANY K with k_K=2*mu*sum(alpha/beta^2)/n: E[1/lam]=O(eps) if k_K>1 (Thm E, corrected Lyapunov log W+psi/W^2 with Perron weights) => no consistent mu-estimator (Cor E'); E[1/lam]>=c eps^(k_K+eta) if k_K<1 (Thm F) => alpha-known information diverges. Pathwise check of generator bounds passed. Open: efficient (alpha-unknown) info divergence for K>=2 (numerics eff/m->1), matching upper bound/estimator (MLE is mixed-normal: observed info random, CV~0.5), k_K=1 borderline, cold-start coefficients. See problem11_dichotomy.md LITERATURE 25 Oct: divergence of mu-information for kappa<=1 is Herrera-Marin Remark 4.8 (Fatou); he states the kappa>1 direction is NOT proved. Gamma shape/Feller threshold k=2*beta*mu/alpha^2 confirmed against Jaisson-Rosenbaum Thm 2.2 (shape 2m*mu; tested, autocorrelation exp(-eps*beta*t) also confirmed). REASSESSMENT 25 Oct: divergence half = Herrera-Marin Remark 4.8; he leaves the converse (kappa>1) unproved. Other session's Theorem A (K=1, stationary) claims it with rates (I have NOT verified its proof). Exact slopes of (1/2) log det I vs log(1/eps): 0.347,0.397,0.404,0.403,0.402 -> (1-k0)/2=0.40 for k0=0.2; -> 0 for k0>=2. K=2 dictionary: A_T matches the K=1 value at equal k=2*mu*m (1.29/1.53/1.79 vs 1.26/1.55/1.78): supports threshold 2*mu*sum(w_k/beta_k)=1. Observation model matters (stationary vs empty start). VERIFICATION 25 Oct (verification_thmA_E_F.md): Lemma H re-derived and holds pathwise in 30/30 (parameter,z) cases; Theorems E and F re-derived: CORRECT given Lemma H; E_pi[A f]=0 and the E/F integral inequalities confirmed by stationary MC (16 independent replicates). GAP in the use of E: Corollary E'/Theorem B compare path laws with the SAME initial state; impossibility is rigorous for the experiment where S_0 (pre-sample history) is given, but for a stationary record with unobserved past one also needs KL(pi_theta||pi_theta') = O(1) (Gamma approx 0.003-0.034; not proved) - same step Herrera-Marin I calls open. Also: the empty-start experiment (the actual streaming setting) has mu-information >= ln T for every k, so the 'mu unlearnable' headline is observation-model specific. UPDATE 25 Oct (theoremA_step2_and_stationary_tv.md): initial-state gap closed for K=1, k0>1: TV(Q,Q') <= sqrt(rho u'I_T u/2) + TV(pi,pi') (Lemma R), and TV(pi_theta,pi_theta') <= C|delta| + C eps^min(1,k0-1/2) via exact characteristic function phi=G*Ftilde (Gamma comparator), imaginary-axis bound |D_eps(-i tau)|<=31.5/alpha, monotone |phi|, and TV <= ||.||_H1/(2 sqrt2). Numerics (FFT inversion of exact ch.f.): TV(pi,pi') = 0.026/0.070 for delta=0.1/0.3, flat in eps from 0.1 to 0.003; TV(pi,Gamma) ~ eps. MY PROOF, NOT REVIEWED; constants not explicit; K>=2, k0<=1 not covered. UPDATE 25 Oct (general_K_impossibility.md): impossibility of consistent mu-estimation for the STATIONARY record with unobserved past now proved for ANY K with k_K>1 (Theorem V: TV(Q,Q') <= C delta sqrt(ln(1/delta))), by a route that bypasses TV(pi_theta,pi_theta'): (1) KL of stationary theta-process vs theta'-dynamics started from pi_theta over a window L+T=O(1/gamma) is O(delta^2) via Theorem E; (2) superposition: process from state s = empty-start + ghost immigrants g_s(t); (3) cluster survival q(s)<=C' gamma e^{-gamma s} from the flow Y'=-BY+alpha(1-e^{-|Y|}) and zeta'=-gamma zeta - r(|Y|) (first-moment bound would lose ln(1/eps)). Verified: flow vs cluster MC (K=1,2), ghost-hit prob decays e^{-gamma L} (K=2 sim). MY PROOF, UNREVIEWED. TV(pi,pi') for K>=2 itself still open. LITERATURE 25 Oct (literature_search_report.md): CIR side: information about the drift constant finite iff a > sigma (Ben Alaya et al. Thm 2.1); MLE defined only for 2a > sigma^2 (Dehtiar et al.); critical case sqrt(log T) rate. Discrete side: all estimation results found are CLSE/OLS; Li 2011: nonzero initial values => CLSE of immigration mean inconsistent; Anne-Lu-Yu-Zhou 2026: OLS intercept inconsistent in local-to-unity affine processes (no Hawkes, no information bound; overlap risk Medium). Herrera-Marin's Wei-Winnicki attribution UNVERIFIED. THM T CONSTANTS 25 Oct (thmT_explicit_constants.md): Theorem T now has an explicit chain: |d|<=19 (true sup 1.143), tail exponent q=k0/(2(1+3/X0))>1/2 (k/(1+r)^2=k0 exactly), certified TV(pi,Gamma)<=Phi/(2 sqrt2); k0=2: 2e-2 (eps=1e-4), 1e-3 (1e-5), 8.6e-5 (1e-6); bound 1e2-1e3 above truth, valid in all tests. Ridge pair: TV<=2.4e-3+0.39 delta (eps<=1e-5, k0=2, delta<=0.3). Phi by floating-point quadrature of hand-proved majorants, not interval arithmetic; KL step evaluated on a grid; informative only for eps<~1e-4. FINAL AUDIT 25 Oct (final_audit.md): the 'no consistent estimator given S0' statements (Thm B, Cor D, Cor E') were stronger than the KL lemma proves: the correct bound is TV(Q) <= TV(pi_theta, pi_theta') + sqrt(rho T u'Iu/2). Rigorous impossibility: K=1 stationary record (Thm T), any K stationary record with unobserved past (Thm V). K>=2 with S0 observed: open.
A13: 12 | B13: C. Lower bound and information limits | C13: Degenerate directions for K > 1 | D13: Determine whether the near-singular direction of the Fisher information is n, μ, or a mixture of the α_k across time scales. | E13: A statement identifying the degenerate eigendirection(s) and how they depend on ε and on the grid. | F13: C3, C4 | G13: P3 Lower bound and simulation | H13: Medium | I13: 3 | J13: 2 | K13: 2, 10 | L13: Done | M13: Draft done 2026-10-25 (needs your re-derivation). I(theta*) has three tiers: top ~1/eps along grad_alpha n=(1/beta_k) (pure n-direction, best determined); K-1 middle 'kernel-shape' directions (sum w_k/beta_k=0) of size O(1) set by the beta-grid via the Hawkes-corrected spectral Gram (checked: 0.0667 pred vs 0.0661 MC, K=2); ridge ~ eps/(mu(k-1)) along (1,-eps*alpha/mu) = mean-rate-preserving mu-n trade (E lam=mu/eps fixed, shape fixed). As eps->0 the RIDGE is the degenerate direction; at moderate eps for K>=3 / tight grids a time-scale MIXTURE is smaller (K=3, beta=(1,2,4): until eps~0.007). Rigorous: ridge Rayleigh bound O(eps) (via Thm E), lambda_max>=(mu/eps-2mu)/|alpha|^2, K=1. Heuristic/numerical: middle tier, eigenvector convergence. See problem12_degenerate_directions.md REASSESSMENT 25 Oct: Herrera-Marin II (2609.38267) Sec 5 reports numerically an 'almost flat direction' from K~5 when fitting sums of exponentials to a long-memory kernel (slow poles trade mass with the baseline; not proved, misspecified setting). Same mechanism as my Problem 2 for the well-specified dictionary (lambda_min(I) falls ~10x per added exponential at r=2). Only a LOWER bound on lambda_min is proved here (Theorem T); a matching UPPER bound as K or the grid ratio grows would turn the flat direction into a theorem.
A14: 13 | B14: D. Drift tracking | C14: Tracking bound with constant step η | D14: Prove E‖θ̂_t − θ*_t‖² ≲ η σ²(ε) + Δ²/η² for a constant-step estimator and drift rate Δ. Check the exponent on η, since it depends on how the drift enters. | E14: A theorem with ε-explicit constants, and a short comparison with Solo (2018) and Hall–Willett (2016). | F14: C5 | G14: P5 Second paper or optional | H14: High | I14: 4 | J14: 3 | K14: 3, 5 | L14: Not started
A15: 14 | B15: D. Drift tracking | C15: Choose the drift model | D15: Choose one: smooth drift, piecewise-constant with jumps, or bounded variation. Each gives a different bound. | E15: One drift model chosen and justified, with reasons for excluding the others. | F15: C5 | G15: P5 Second paper or optional | H15: Medium | I15: 1 | J15: 0.5 | L15: Done | M15: DECISION 2026-10-25: bounded variation as piecewise-Lipschitz class (Lipschitz rate Delta, <=J jumps of size <=D, box mu_t in [mu,c_mu*mu], eps_t in [eps,c_eps*eps], fixed reference Fisher norm). Target for P13: eta*sigma^2 + Delta^2/eta^2 (response of a time-varying-gain filter, gain eta*mu_t/eps) + J*D^2/(eta*T); sigma^2=r/(2*eff) (K=1 alpha known: mu/(2*eps*m)). Verified numerically (causal sampling): sinusoid, triangle, ramp, random walk, jumps; K=1,2,3 (grids (1,2),(1,4),(1,2,4),(1,3,9)); noise coeff r/(2 eff) within 3-13% in window; linear window eta<=theta_k*mu^2/a, theta_k~0.013-0.03 (k-dependent). Problem 5 recursion verbatim cannot track drift (needs forgetting). RETRACTED c_lag~1.8: extra lag for alpha-unknown is an amplitude effect of the data-driven preconditioner (1.3-1.75x at A=0.2-0.5, ->1 as A->0), absent with fixed preconditioner. Metric equivalence kappa_I: K=1 7-9, K=2 10-11 (mu x1.5), eps-independent. Hall-Willett VERIFIED from LaTeX source (adversarial regret C(1+sum||lam_{t+1}-Phi_t(lam_t)||_2)*sqrt(T): variation measure is a path length relative to known dynamics, norm not squared; no parameter-drift model). Solo (Piggott-Solo ICASSP 2018) NOT read: closed access, no OA copy (needs your library). Open: K>=4, eps<0.4 for K>=2, analytic derivation of the adaptive-preconditioner excess. See problem14_drift_model.md CLEANUP 25 Oct: stale c_lag / amplitude-independence / K=2 bias-ratio statements struck in the note; noise convention (sigma^2=a=r/(2 eff)); path-length bound V^2/(eta T) (factor 1/2 not derived); jump term units. Label clashes resolved in LABELS.md.
A16: 15 | B16: D. Drift tracking | C16: Optimal step size and its ε-dependence | D16: Show how criticality shifts the best step size η, and what that implies for practical tuning. | E16: A formula or scaling law for η*(ε, Δ) and a simulation that confirms it. | F16: C5 | G16: P5 Second paper or optional | H16: Medium | I16: 2 | J16: 1 | K16: 13 | L16: Done | M16: Draft done 2026-10-25, CONDITIONAL on Problem 13 (tracking bound not proved; built on measured MSE structure from P14). MSE(eta)=a*eta+B(eta), a=r/(2*eff). Smooth drift fast regime: eta*=(Delta_e^2/a)^(1/3) ~ eps^(4/3)*Delta^(2/3) (k>1), MSE*=1.5*a*eta*; jumps: eta*=D*mu/sqrt(2*a*L_e) ~ eps^(3/2); k<1 exponents 1+k/3, 1+k/2. Window cap eta<=theta*mu^2/a ~ eps^2 binds as eps->0. Tracking beats static estimator only if P*eff*(A*mu)^2 >~ 16 (checked: 8.7 no gain, 22.6 modest, 34.7 gain 26%). alpha unknown shifts eta* down by ~k^(-1/3). Sim (K=1): smooth alpha-known eta_opt 0.00292/0.00179/0.00089 vs predicted 0.00295/0.00193/0.00095 at eps 0.4/0.3/0.2; jumps within 15-27%. Not done: K>=2 eta_opt, eps<0.2, pure power-law regime. See problem15_step_size.md
A17: 16 | B17: E. Misspecification | C17: Exact KL pseudo-truth | D17: Characterize θ† for the Hawkes KL (E* ∫ [λ* log(λ*/λ_θ) − (λ* − λ_θ)] dt), not the quadratic surrogate used in prior work, and prove existence and uniqueness. | E17: A theorem on existence and uniqueness of θ†, with the first-order condition written out. | F17: C6 | G17: P5 Second paper or optional | H17: Medium | I17: 4 | J17: 2 | L17: Not started
A18: 17 | B18: E. Misspecification | C18: Online convergence to θ† | D18: Show the online estimator converges to θ† under misspecification, with the stability constraint n ≤ 1−ε active. | E18: A convergence theorem (almost sure or in probability) with the active-constraint case handled. | F18: C6 | G18: P5 Second paper or optional | H18: Medium | I18: 4 | J18: 3 | K18: 5, 16 | L18: Not started
A19: 18 | B19: E. Misspecification | C19: Bias of n(θ†) versus K | D19: For a power-law truth on a geometric β-grid, give an explicit rate for the bias of n(θ†) as K grows. This is a rational-approximation problem for a completely monotone kernel with a branch point. | E19: An explicit rate (or a numerically supported conjecture) for the bias as a function of K and grid ratio. | F19: C6 | G19: P5 Second paper or optional | H19: Low | I19: 4 | J19: 3 | K19: 16 | L19: Not started
A20: 19 | B20: F. Validation | C20: Simulation study | D20: Simulate with Ogata thinning using known (μ, α, β). Sweep ε and T and check that regret and error follow the predicted scalings, including the burn-in. | E20: Plots of error and regret versus T for several ε, with fitted slopes compared with theory. | F20: All | G20: P3 Lower bound and simulation | H20: High | I20: 2 | J20: 2 | K20: 5 | L20: Not started
A21: 20 | B21: F. Validation | C21: Real-data check | D21: Test on NSE or Bank Nifty tick or order-flow data. Fit the dictionary, report the estimated n, show the effect of misspecification, and show tracking behaviour across regime changes. Needs access to suitable tick data. | E21: A figure of n̂(t) over a trading period, with a comment on regime shifts and on bias relative to a batch fit. | F21: All | G21: P4 Stretch and validation | H21: Medium | I21: 3 | J21: 3 | K21: 19 | L21: Not started
A22: 21 | B22: F. Validation | C22: Baselines to beat | D22: Implement batch MLE, Hall–Willett mirror descent and Solo's fixed-gain estimator, and compare accuracy and per-event cost with your method. | E22: A comparison table of error and runtime on the same simulated and real datasets. | F22: All | G22: P4 Stretch and validation | H22: Medium | I22: 2 | J22: 2 | K22: 19 | L22: Not started
A23: 22 | B23: G. Literature | C23: Read the core papers and write 'difference from' statements | D23: Read the papers listed on the Literature sheet in the suggested order and, for each, write one paragraph on how your result differs from theirs. | E23: A related-work section draft with one 'difference from' paragraph per paper. | F23: All | G23: P0 Parallel | H23: High | I23: 2 | J23: 2 | L23: Not started
A24: 23 | B24: G. Literature | C24: Check the items not verified | D24: Check Zhang 2023 and Wang 2023 online or sequential estimators, online EM for Hawkes (Lemonnier–Vayatis, Zhou–Zha–Song), Bacry–Muzy–Delattre–Hoffmann, and the citation trees of Yang et al. (2017) and Hall–Willett (2016). | E24: A list of anything that anticipates your results, and an update of the overlap-risk column on the Literature sheet. | F24: All | G24: P0 Parallel | H24: Medium | I24: 2 | J24: 1.5 | L24: Not started

Sheet Summary
A1: Research problem tracker: summary
A2: All figures below are formulas driven by the Problems sheet. Change Status, Priority or Est. weeks there and this sheet updates.
A4: Overall
A5: Total problems | B5: =COUNTA(Problems!$A$2:$A$24)
A6: Total estimated weeks | B6: =SUM(Problems!$J$2:$J$24)
A7: Weeks completed (Status = Done) | B7: =SUMIFS(Problems!$J$2:$J$24,Problems!$L$2:$L$24,"Done")
A8: Percent complete (weighted by weeks) | B8: =IFERROR(B7/B6,0)
A9: Critical-priority problems still open | B9: =COUNTIFS(Problems!$H$2:$H$24,"Critical",Problems!$L$2:$L$24,"<>Done")
A11: Status | B11: Problems | C11: Est. weeks
A12: Not started | B12: =COUNTIF(Problems!$L$2:$L$24,A12) | C12: =SUMIFS(Problems!$J$2:$J$24,Problems!$L$2:$L$24,A12)
A13: In progress | B13: =COUNTIF(Problems!$L$2:$L$24,A13) | C13: =SUMIFS(Problems!$J$2:$J$24,Problems!$L$2:$L$24,A13)
A14: Blocked | B14: =COUNTIF(Problems!$L$2:$L$24,A14) | C14: =SUMIFS(Problems!$J$2:$J$24,Problems!$L$2:$L$24,A14)
A15: Done | B15: =COUNTIF(Problems!$L$2:$L$24,A15) | C15: =SUMIFS(Problems!$J$2:$J$24,Problems!$L$2:$L$24,A15)
A16: Total | B16: =SUM(B12:B15) | C16: =SUM(C12:C15)
A18: Section | B18: Problems | C18: Est. weeks | D18: Done
A19: A. Foundations | B19: =COUNTIF(Problems!$B$2:$B$24,A19) | C19: =SUMIFS(Problems!$J$2:$J$24,Problems!$B$2:$B$24,A19) | D19: =COUNTIFS(Problems!$B$2:$B$24,A19,Problems!$L$2:$L$24,"Done")
A20: B. Upper bound | B20: =COUNTIF(Problems!$B$2:$B$24,A20) | C20: =SUMIFS(Problems!$J$2:$J$24,Problems!$B$2:$B$24,A20) | D20: =COUNTIFS(Problems!$B$2:$B$24,A20,Problems!$L$2:$L$24,"Done")
A21: C. Lower bound and information limits | B21: =COUNTIF(Problems!$B$2:$B$24,A21) | C21: =SUMIFS(Problems!$J$2:$J$24,Problems!$B$2:$B$24,A21) | D21: =COUNTIFS(Problems!$B$2:$B$24,A21,Problems!$L$2:$L$24,"Done")
A22: D. Drift tracking | B22: =COUNTIF(Problems!$B$2:$B$24,A22) | C22: =SUMIFS(Problems!$J$2:$J$24,Problems!$B$2:$B$24,A22) | D22: =COUNTIFS(Problems!$B$2:$B$24,A22,Problems!$L$2:$L$24,"Done")
A23: E. Misspecification | B23: =COUNTIF(Problems!$B$2:$B$24,A23) | C23: =SUMIFS(Problems!$J$2:$J$24,Problems!$B$2:$B$24,A23) | D23: =COUNTIFS(Problems!$B$2:$B$24,A23,Problems!$L$2:$L$24,"Done")
A24: F. Validation | B24: =COUNTIF(Problems!$B$2:$B$24,A24) | C24: =SUMIFS(Problems!$J$2:$J$24,Problems!$B$2:$B$24,A24) | D24: =COUNTIFS(Problems!$B$2:$B$24,A24,Problems!$L$2:$L$24,"Done")
A25: G. Literature | B25: =COUNTIF(Problems!$B$2:$B$24,A25) | C25: =SUMIFS(Problems!$J$2:$J$24,Problems!$B$2:$B$24,A25) | D25: =COUNTIFS(Problems!$B$2:$B$24,A25,Problems!$L$2:$L$24,"Done")
A26: Total | B26: =SUM(B19:B25) | C26: =SUM(C19:C25) | D26: =SUM(D19:D25)
A28: Priority | B28: Problems | C28: Est. weeks | D28: Done
A29: Critical | B29: =COUNTIF(Problems!$H$2:$H$24,A29) | C29: =SUMIFS(Problems!$J$2:$J$24,Problems!$H$2:$H$24,A29) | D29: =COUNTIFS(Problems!$H$2:$H$24,A29,Problems!$L$2:$L$24,"Done")
A30: High | B30: =COUNTIF(Problems!$H$2:$H$24,A30) | C30: =SUMIFS(Problems!$J$2:$J$24,Problems!$H$2:$H$24,A30) | D30: =COUNTIFS(Problems!$H$2:$H$24,A30,Problems!$L$2:$L$24,"Done")
A31: Medium | B31: =COUNTIF(Problems!$H$2:$H$24,A31) | C31: =SUMIFS(Problems!$J$2:$J$24,Problems!$H$2:$H$24,A31) | D31: =COUNTIFS(Problems!$H$2:$H$24,A31,Problems!$L$2:$L$24,"Done")
A32: Low | B32: =COUNTIF(Problems!$H$2:$H$24,A32) | C32: =SUMIFS(Problems!$J$2:$J$24,Problems!$H$2:$H$24,A32) | D32: =COUNTIFS(Problems!$H$2:$H$24,A32,Problems!$L$2:$L$24,"Done")
A34: Estimates of difficulty, priority and weeks are my judgement for a single researcher working sequentially, not measured data. Edit them on the Problems sheet. Weeks are summed, so the total is not a critical-path estimate.

Sheet Roadmap
A1: Suggested order of work
A2: Phase totals pull from the Problems sheet. Item lists show the suggested working order inside each phase.
A4: Phase | B4: What this phase is for | C4: Suggested order (IDs) | D4: Problems | E4: Est. weeks | F4: Done
A5: P0 Parallel | B5: Literature work, run alongside everything else. | C5: 22, 23 | D5: =COUNTIF(Problems!$G$2:$G$24,A5) | E5: =SUMIFS(Problems!$J$2:$J$24,Problems!$G$2:$G$24,A5) | F5: =COUNTIFS(Problems!$G$2:$G$24,A5,Problems!$L$2:$L$24,"Done")
A6: P1 Core feasibility | B6: Order: 10, then 1, then 3, then 5. If K = 1 Fisher information is tractable and the stochastic analysis closes, you have the core of a paper. | C6: 10, 1, 3, 5 | D6: =COUNTIF(Problems!$G$2:$G$24,A6) | E6: =SUMIFS(Problems!$J$2:$J$24,Problems!$G$2:$G$24,A6) | F6: =COUNTIFS(Problems!$G$2:$G$24,A6,Problems!$L$2:$L$24,"Done")
A7: P2 Complete upper bound | B7: Finish the upper bound with explicit ε-dependence. | C7: 7, 8, 6, 2, 4 | D7: =COUNTIF(Problems!$G$2:$G$24,A7) | E7: =SUMIFS(Problems!$J$2:$J$24,Problems!$G$2:$G$24,A7) | F7: =COUNTIFS(Problems!$G$2:$G$24,A7,Problems!$L$2:$L$24,"Done")
A8: P3 Lower bound and simulation | B8: Add the matching lower bound and confirm scalings by simulation. | C8: 9, 12, 19 | D8: =COUNTIF(Problems!$G$2:$G$24,A8) | E8: =SUMIFS(Problems!$J$2:$J$24,Problems!$G$2:$G$24,A8) | F8: =COUNTIFS(Problems!$G$2:$G$24,A8,Problems!$L$2:$L$24,"Done")
A9: P4 Stretch and validation | B9: Item 11 is the stretch goal that makes the paper strong. Add baselines and real data. | C9: 11, 21, 20 | D9: =COUNTIF(Problems!$G$2:$G$24,A9) | E9: =SUMIFS(Problems!$J$2:$J$24,Problems!$G$2:$G$24,A9) | F9: =COUNTIFS(Problems!$G$2:$G$24,A9,Problems!$L$2:$L$24,"Done")
A10: P5 Second paper or optional | B10: Drift tracking and misspecification. Drop to a second paper if time runs short. | C10: 13, 14, 15, 16, 17, 18 | D10: =COUNTIF(Problems!$G$2:$G$24,A10) | E10: =SUMIFS(Problems!$J$2:$J$24,Problems!$G$2:$G$24,A10) | F10: =COUNTIFS(Problems!$G$2:$G$24,A10,Problems!$L$2:$L$24,"Done")
A11: Total | D11: =SUM(D5:D10) | E11: =SUM(E5:E10) | F11: =SUM(F5:F10)
A13: Working order, with titles pulled from the Problems sheet
A14: Step | B14: ID | C14: Problem | D14: Priority | E14: Est. weeks | F14: Status
A15: 1 | B15: 10 | C15: =IFERROR(INDEX(Problems!$C$2:$C$24,MATCH($B15,Problems!$A$2:$A$24,0)),"") | D15: =IFERROR(INDEX(Problems!$H$2:$H$24,MATCH($B15,Problems!$A$2:$A$24,0)),"") | E15: =IFERROR(INDEX(Problems!$J$2:$J$24,MATCH($B15,Problems!$A$2:$A$24,0)),"") | F15: =IFERROR(INDEX(Problems!$L$2:$L$24,MATCH($B15,Problems!$A$2:$A$24,0)),"")
A16: 2 | B16: 1 | C16: =IFERROR(INDEX(Problems!$C$2:$C$24,MATCH($B16,Problems!$A$2:$A$24,0)),"") | D16: =IFERROR(INDEX(Problems!$H$2:$H$24,MATCH($B16,Problems!$A$2:$A$24,0)),"") | E16: =IFERROR(INDEX(Problems!$J$2:$J$24,MATCH($B16,Problems!$A$2:$A$24,0)),"") | F16: =IFERROR(INDEX(Problems!$L$2:$L$24,MATCH($B16,Problems!$A$2:$A$24,0)),"")
A17: 3 | B17: 3 | C17: =IFERROR(INDEX(Problems!$C$2:$C$24,MATCH($B17,Problems!$A$2:$A$24,0)),"") | D17: =IFERROR(INDEX(Problems!$H$2:$H$24,MATCH($B17,Problems!$A$2:$A$24,0)),"") | E17: =IFERROR(INDEX(Problems!$J$2:$J$24,MATCH($B17,Problems!$A$2:$A$24,0)),"") | F17: =IFERROR(INDEX(Problems!$L$2:$L$24,MATCH($B17,Problems!$A$2:$A$24,0)),"")
A18: 4 | B18: 5 | C18: =IFERROR(INDEX(Problems!$C$2:$C$24,MATCH($B18,Problems!$A$2:$A$24,0)),"") | D18: =IFERROR(INDEX(Problems!$H$2:$H$24,MATCH($B18,Problems!$A$2:$A$24,0)),"") | E18: =IFERROR(INDEX(Problems!$J$2:$J$24,MATCH($B18,Problems!$A$2:$A$24,0)),"") | F18: =IFERROR(INDEX(Problems!$L$2:$L$24,MATCH($B18,Problems!$A$2:$A$24,0)),"")
A19: 5 | B19: 7 | C19: =IFERROR(INDEX(Problems!$C$2:$C$24,MATCH($B19,Problems!$A$2:$A$24,0)),"") | D19: =IFERROR(INDEX(Problems!$H$2:$H$24,MATCH($B19,Problems!$A$2:$A$24,0)),"") | E19: =IFERROR(INDEX(Problems!$J$2:$J$24,MATCH($B19,Problems!$A$2:$A$24,0)),"") | F19: =IFERROR(INDEX(Problems!$L$2:$L$24,MATCH($B19,Problems!$A$2:$A$24,0)),"")
A20: 6 | B20: 8 | C20: =IFERROR(INDEX(Problems!$C$2:$C$24,MATCH($B20,Problems!$A$2:$A$24,0)),"") | D20: =IFERROR(INDEX(Problems!$H$2:$H$24,MATCH($B20,Problems!$A$2:$A$24,0)),"") | E20: =IFERROR(INDEX(Problems!$J$2:$J$24,MATCH($B20,Problems!$A$2:$A$24,0)),"") | F20: =IFERROR(INDEX(Problems!$L$2:$L$24,MATCH($B20,Problems!$A$2:$A$24,0)),"")
A21: 7 | B21: 6 | C21: =IFERROR(INDEX(Problems!$C$2:$C$24,MATCH($B21,Problems!$A$2:$A$24,0)),"") | D21: =IFERROR(INDEX(Problems!$H$2:$H$24,MATCH($B21,Problems!$A$2:$A$24,0)),"") | E21: =IFERROR(INDEX(Problems!$J$2:$J$24,MATCH($B21,Problems!$A$2:$A$24,0)),"") | F21: =IFERROR(INDEX(Problems!$L$2:$L$24,MATCH($B21,Problems!$A$2:$A$24,0)),"")
A22: 8 | B22: 2 | C22: =IFERROR(INDEX(Problems!$C$2:$C$24,MATCH($B22,Problems!$A$2:$A$24,0)),"") | D22: =IFERROR(INDEX(Problems!$H$2:$H$24,MATCH($B22,Problems!$A$2:$A$24,0)),"") | E22: =IFERROR(INDEX(Problems!$J$2:$J$24,MATCH($B22,Problems!$A$2:$A$24,0)),"") | F22: =IFERROR(INDEX(Problems!$L$2:$L$24,MATCH($B22,Problems!$A$2:$A$24,0)),"")
A23: 9 | B23: 4 | C23: =IFERROR(INDEX(Problems!$C$2:$C$24,MATCH($B23,Problems!$A$2:$A$24,0)),"") | D23: =IFERROR(INDEX(Problems!$H$2:$H$24,MATCH($B23,Problems!$A$2:$A$24,0)),"") | E23: =IFERROR(INDEX(Problems!$J$2:$J$24,MATCH($B23,Problems!$A$2:$A$24,0)),"") | F23: =IFERROR(INDEX(Problems!$L$2:$L$24,MATCH($B23,Problems!$A$2:$A$24,0)),"")
A24: 10 | B24: 9 | C24: =IFERROR(INDEX(Problems!$C$2:$C$24,MATCH($B24,Problems!$A$2:$A$24,0)),"") | D24: =IFERROR(INDEX(Problems!$H$2:$H$24,MATCH($B24,Problems!$A$2:$A$24,0)),"") | E24: =IFERROR(INDEX(Problems!$J$2:$J$24,MATCH($B24,Problems!$A$2:$A$24,0)),"") | F24: =IFERROR(INDEX(Problems!$L$2:$L$24,MATCH($B24,Problems!$A$2:$A$24,0)),"")
A25: 11 | B25: 12 | C25: =IFERROR(INDEX(Problems!$C$2:$C$24,MATCH($B25,Problems!$A$2:$A$24,0)),"") | D25: =IFERROR(INDEX(Problems!$H$2:$H$24,MATCH($B25,Problems!$A$2:$A$24,0)),"") | E25: =IFERROR(INDEX(Problems!$J$2:$J$24,MATCH($B25,Problems!$A$2:$A$24,0)),"") | F25: =IFERROR(INDEX(Problems!$L$2:$L$24,MATCH($B25,Problems!$A$2:$A$24,0)),"")
A26: 12 | B26: 19 | C26: =IFERROR(INDEX(Problems!$C$2:$C$24,MATCH($B26,Problems!$A$2:$A$24,0)),"") | D26: =IFERROR(INDEX(Problems!$H$2:$H$24,MATCH($B26,Problems!$A$2:$A$24,0)),"") | E26: =IFERROR(INDEX(Problems!$J$2:$J$24,MATCH($B26,Problems!$A$2:$A$24,0)),"") | F26: =IFERROR(INDEX(Problems!$L$2:$L$24,MATCH($B26,Problems!$A$2:$A$24,0)),"")
... A37: 23 | B37: 23 | C37: =IFERROR(INDEX(Problems!$C$2:$C$24,MATCH($B37,Problems!$A$2:$A$24,0)),"") | D37: =IFERROR(INDEX(Problems!$H$2:$H$24,MATCH($B37,Problems!$A$2:$A$24,0)),"") | E37: =IFERROR(INDEX(Problems!$J$2:$J$24,MATCH($B37,Problems!$A$2:$A$24,0)),"") | F37: =IFERROR(INDEX(Problems!$L$2:$L$24,MATCH($B37,Problems!$A$2:$A$24,0)),"")

Sheet Literature
A1: Read order | B1: Paper | C1: Authors / venue | D1: Link or id | E1: Relevant to problem IDs | F1: What to extract | G1: Overlap risk | H1: Read status
A2: 1 | B2: Learning the exogenous rate but not the distance to criticality in nearly unstable heavy-tailed Hawkes processes | C2: Herrera-Marín, arXiv, Sept 2026 (unrefereed) | D2: arXiv 2609.38268 | E2: 9, 10, 11, 12 | F2: Theorem 2.2 (kernel-agnostic KL bound), Theorem 4.1, Remark 4.8 (the half-open Feller-type dichotomy). | G2: High | H2: Read 25 Oct 2026 (full text). Thm 2.2, Cor 2.3, Thm 4.1, Rem 4.8 re-derived and tested numerically; overlap with C3 and the kappa<=1 half of C4 confirmed. See literature_crosscheck.md.
A3: 2 | B3: Minimax and adaptive inference for branching ratios under long memory | C3: Herrera-Marín, arXiv, Sept 2026 (unrefereed) | D3: arXiv 2609.38267 | E3: 16, 17, 18 | F3: Section 5: pseudo-true branching ratio for sums of K exponentials, quadratic surrogate, flat directions. | G3: High | H3: Partly read 25 Oct 2026 (abstract, Sec 5, Sec 6.2 only). Thm 3.1 and its proof NOT checked.
A4: 3 | B4: Tracking Dynamic Point Processes on Networks | C4: Hall and Willett, IEEE Trans. Inf. Theory 62(7), 2016 | D4: arXiv 1409.0031 | E4: 5, 13, 21 | F4: Dynamic mirror descent setup, √T tracking regret and its assumptions. | G4: Medium | H4: Partly read 25 Oct 2026 (Thm 1 statement, Appendix C parametrisation). Proof NOT checked.
A5: 4 | B5: Online Learning for Multivariate Hawkes Processes | C5: Yang, Etesami, He, Kiyavash, NeurIPS 2017 | D5: proceedings.neurips.cc (2017, paper 92a0e7a4…) | E5: 5, 6, 21 | F5: How log T is obtained (Tikhonov regularization, discretization, truncation) and what that costs. | G5: Medium | H5: Not read (the arXiv version in the next row was read instead).
A6: 5 | B6: Nonparametric Hawkes Processes: Online Estimation and Generalization Bounds | C6: Yang, Etesami, He, Kiyavash, arXiv | D6: arXiv 1801.08273 | E6: 5, 6 | F6: Journal-version regret and stability claims; marked extension. | G6: Medium | H6: Read 25 Oct 2026 (assumptions, eq. (8)-(9), Thm 2, Cor 1). Proof of Thm 2 only skimmed. See literature_crosscheck.md.
A7: 6 | B7: Non-Negative Online Estimation for Hawkes Process Networks | C7: Piggott and Solo, ICASSP 2018, pp. 6333-6337 (listed earlier as "Solo") | D7: IEEE Xplore 8462138 | E7: 13, 15, 21 | F7: Fixed-gain recursive estimator on an exponential-type basis; closest prior art for constant step size. | G7: High | H7: Reading: abstract read 25 Oct 2026 (via OpenAlex); full text NOT obtained. Fixed-gain exponentially weighted least squares on a Laguerre basis, non-negativity preserving, two time scales, simulations; abstract states no regret bound or near-critical analysis. See literature_search_report.md.
A8: 7 | B8: Hawkes Identification with a Prescribed Causal Basis | C8: Rong and Nair, arXiv, Feb 2026 | D8: arXiv 2602.20795 | E8: 16, 17 | F8: Pseudo-true parameters and CLTs under misspecification (least squares, batch). | G8: Medium | H8: Not started
A9: 8 | B9: A non-local estimator for locally stationary Hawkes processes | C9: Deschatre, Gruet, Lotz, arXiv, June 2025 | D9: arXiv 2506.02631 | E9: 13, 14 | F9: Batch MLE theory for time-varying baseline and reproduction rate. | G9: Medium | H9: Not started
A10: 9 | B10: Limit theorems for nearly unstable Hawkes processes | C10: Jaisson and Rosenbaum, Ann. Appl. Probab. 25(2), 2015 | D10: arXiv 1310.2033 | E10: 10, 11 | F10: Integrated-CIR scaling limit when T(1−a_T) → λ; the starting point for the information analysis. | G10: Low | H10: Read 25 Oct 2026 (assumptions, Prop 2.1-2.2, Thm 2.2, heuristic derivation); tested against exact K=1 Hawkes. Proof NOT checked.
A11: 10 | B11: Logarithmic regret algorithms for online convex optimization | C11: Hazan, Agarwal, Kale, Machine Learning 69, 2007 | D11: ONS reference | E11: 5, 6 | F11: ONS analysis and where exp-concavity is used, to see exactly what must be replaced. | G11: Low | H11: Original returned HTTP 403. Read Hazan's monograph arXiv 1909.05207 Sec 4.2/4.4 instead (criterion, Thm 4.5 statement); proof not re-derived.
A12: 11 | B12: Functional limit theorems for Hawkes processes | C12: Horst and Xu, arXiv, 2024 | D12: arXiv 2401.11495 | E12: 10, 11 | F12: Critical Hawkes processes behave like CIR without mean reversion. | G12: Low | H12: Not started
A13: 12 | B13: Change Point Detection and Mean-Field Dynamics of Variable Productivity Hawkes Processes | C13: Kresin, Baeumer, Phillips, arXiv, Dec 2025 | D13: arXiv 2512.20068 | E13: 13, 14 | F13: Post-change boundary-layer Fisher information; ingredient for the variance term in tracking. | G13: Medium | H13: Not started
... A19: 18 | B19: Sequential Change-Point Detection for Mutually Exciting Point Processes | C19: arXiv | D19: arXiv 2102.05724 | E19: 14 | F19: CUSUM-type detection; pre-change parameters from batch MLE. | G19: Low | H19: Not started
A20: - | B20: Zhang et al. 2023 online estimator; Wang et al. 2023 sequential estimator | C20: To check | D20: Search needed | E20: 23 | F20: Not verified. Could anticipate parts of the proposal. | G20: Unknown | H20: Not started
A21: - | B21: Online EM for Hawkes (Lemonnier and Vayatis; Zhou, Zha, Song) | C21: To check | D21: Search needed | E21: 23 | F21: Not verified. | G21: Unknown | H21: Not started
A22: - | B22: Bacry, Muzy, Delattre, Hoffmann; Cartea, Cohen, Labyad (arXiv 2111.10637) | C22: To check | D22: Search needed | E22: 23 | F22: Not verified; SGD for Hawkes least-squares contrast. | G22: Unknown | H22: Not started
A23: - | B23: Citation trees of Yang et al. (2017) and Hall–Willett (2016) | C23: To check | D23: Google Scholar | E23: 23 | F23: Look for exponential-dictionary online estimation papers. | G23: Unknown | H23: Not started
A24: 19 | B24: Two methods of estimation of the drift parameters of the Cox-Ingersoll-Ross process: continuous observations | C24: Dehtiar, Mishura, Ralchenko, arXiv, May 2020 | D24: arXiv 2005.05262 | E24: 10, 11 | F24: MLE of (a,b) defined only for 2a > sigma^2; stationary Gamma law of shape 2a/sigma^2; MLE formula uses int dr/r and int dt/r (denominator int r * int 1/r - T^2 mirrors det I_T). | G24: Medium | H24: Reading: abstract, Prop 1 and Section 3 read 25 Oct 2026; proofs and the alternative estimator not read.
A25: 20 | B25: Near-Unit-Root Theory for Affine Processes | C25: Anne, Lu, Yu, Zhou, arXiv, 27 May 2026 | D25: arXiv 2605.27859 | E25: 10, 11, 18 | F25: CIR limit of local-to-unity discrete-time affine processes with a Feller remark (2mu >= sigma^2); OLS intercept inconsistent in the local-to-unity regime. No Hawkes (0 hits), OLS only, no likelihood information or lower bound. | G25: Medium | H25: Reading: abstract, introduction, Thm 1 discussion and parts of Thm 3-4 read 25 Oct 2026 (71 pages, mostly unread).
A26: 21 | B26: Asymptotics of nearly critical Galton-Watson processes with immigration | C26: Kevei, Acta Sci. Math. (Szeged) 77 (2011) 681-702 | D26: arXiv 1107.2440 | E26: 11 | F26: Limit laws: Poisson/compound Poisson when offspring second factorial moment / (1-rho_n) -> 0, negative binomial (discrete Gamma) when it is of the same order. Distribution only, no estimation. | G26: Low | H26: Reading: abstract, introduction, Sections 2.1-2.2 discussion read 25 Oct 2026; proofs not read.
A27: 22 | B27: A fluctuation limit theorem of branching processes with immigration and statistical applications | C27: Ma, arXiv, 2009 | D27: arXiv 0906.2586 | E27: 11 | F27: Survey of the CLSE literature for nearly critical GWI (Sriram 1994: branching-diffusion limit for positive variance; Ispany et al. 2005: n^{3/2} normal for vanishing variance); Thm 3.2: CLSE of (m_n, omega_n). | G27: Low | H27: Reading: abstract, introduction, Thm 3.2 read 25 Oct 2026; proofs not read.
A28: 23 | B28: Discrete CLSE papers (abstracts only): Wei-Winnicki 1990; Ispany-Pap-van Zuijlen 2005; Li 2011 | C28: Ann. Statist. 18 (1990); Adv. Appl. Probab. 37 (2005); Commun. Statist. Theory Methods (2011) | D28: DOI 10.1214/aos/1176347876; 10.1017/s000186780000029x; 10.1080/03610926.2010.500109 | E28: 11 | F28: Li 2011: with non-zero initial values the CLSE of the immigration mean is not consistent (nearly critical Jirina). Wei-Winnicki abstract states only the aim; Herrera-Marin I attributes to them inconsistency of an immigration-mean estimator in the critical case: UNVERIFIED and in conflict with another summary. | G28: Low | H28: Reading: abstracts only (OpenAlex), 25 Oct 2026. Full texts not obtained.
A29: 24 | B29: Regret / redundancy lower bounds: Rissanen 1984 (IEEE IT 30), Rissanen 1986 (Ann. Statist. 14), Merhav-Feder 1998 (IEEE IT 44) | C29: Rissanen; Merhav and Feder | D29: DOI 10.1109/TIT.1984.1056936; 10.1214/aos/1176350051; 10.1109/18.720534 | E29: 9, 5, 6 | F29: Classical (d/2) log n-type lower bounds are for fixed parameters; no Hawkes- or point-process-specific minimax regret lower bound found; none for a triangular array with eps -> 0. | G29: Unknown | H29: Reading: abstracts only; Merhav-Feder PDF host failed TLS verification (not bypassed). Hypotheses of the Rissanen theorems not checked.
B31: Details come from my research summary of 24 Oct 2026. Re-check every claim against the primary source before citing. Herrera-Marín papers are unrefereed arXiv preprints. Overlap risk is my judgement. Updated 25 Oct 2026: rows 7 and 17 corrected, rows 24-29 added from literature_search_report.md; most new entries were read only in part (see Read status).

Sheet Topic
A1: Research topic statement
A3: Working title | B3: Online estimation of near-critical linear Hawkes processes with an exponential dictionary: regret, information limits and tracking as a function of the distance to criticality
A4: Model | B4: λ_t(θ) = μ + Σ_k α_k S_k(t), dS_k = −β_k S_k dt + dN_t, n(θ) = Σ_k α_k/β_k, with a fixed grid β_1 < … < β_K.
A5: Problem | B5: Events arrive as a stream. The state (S_1, …, S_K) is exact and has O(K) size, with no truncation window. The goal is an estimator θ̂_i, updated per event, that is statistically sound even when the true branching ratio n is close to 1, which is where real financial order-flow fits land.
A6: Gap | B6: Online Hawkes estimators exist (Hall–Willett, Yang et al., Solo), but their guarantees hide the dependence on ε = 1 − n inside constants. They are discretized or truncated, and none comes with a lower bound. Near-critical information limits are known for heavy-tailed kernels, but the light-tailed exponential case is open as a theorem.
A7: One-sentence version | B7: We give the first estimator-level theory, with matching upper and lower bounds, for streaming estimation of light-tailed Hawkes processes as the branching ratio approaches 1.
A9: Proposed contributions
A10: C1: Curvature and algorithm | B10: Show that the per-event loss is convex in (μ, α) but not exp-concave, because its Hessian has rank one. Replace the adversarial ONS claim with a stochastic analysis, using Fisher-preconditioned online Newton or recursive MLE on Θ_ε with martingale concentration.
A11: C2: ε-explicit upper bound | B11: Prove regret or estimation error of the form (d/2) log T + C log(1/ε) + burn-in(με), with d = K + 1.
A12: C3: Matching lower bound | B12: A two-point argument based on KL ≲ δ² T μ (1−n), showing which directions are unlearnable when T μ (1−n) = O(1).
A13: C4: Light-tailed information dichotomy | B13: Establish when baseline information diverges or stays bounded in the nearly unstable exponential regime (1−n_T ≍ T⁻¹), via the CIR scaling limit.
A14: C5: Tracking under drift | B14: A bound of the form E‖θ̂_t − θ*_t‖² ≲ η σ²(ε) + Δ²/η² for constant step size η and drift rate Δ.
A15: C6: Misspecification (corollary) | B15: Convergence to the KL pseudo-true parameter θ† when the true kernel is a power law, and the bias of n(θ†) as K grows.
A17: Everything described as 'prove' is a target, not a result. C1 and C2 depend on a curvature argument that you should re-derive yourself; C4 depends on a conjecture that has not been verified.

Sheet Legend
A1: How to use this workbook
A3: Blue text | B3: Cells you are meant to edit: Priority, Difficulty, Est. weeks, Status, Notes on the Problems sheet; Read status on the Literature sheet; the ID column in the Roadmap working order.
A4: Black text | B4: Fixed content (problem descriptions, criteria for being done).
A5: Green text | B5: Formulas that read from another sheet (Summary and Roadmap).
A6: Status | B6: Not started, In progress, Blocked, Done. Pick from the dropdown; Summary and Roadmap update automatically.
A7: Est. weeks | B7: My rough guess for one researcher working on that item alone. It is an assumption, not data. Overwrite with your own numbers.
A8: Difficulty | B8: 1 (routine) to 5 (open research problem). My judgement.
A9: Priority | B9: Critical = decides whether the paper exists; High = needed for the main theorems; Medium = needed for completeness; Low = optional or second paper.
A10: Contribution | B10: C1 to C6 refer to the contributions listed on the Topic sheet.
A11: Depends on | B11: Problem IDs that should be finished, or at least understood, before this one.
